personarag/__init__.py
personarag/core.py
personarag/gate.py
semantic_lexicon/__init__.py
semantic_lexicon/cli.py
semantic_lexicon/compliance.py
semantic_lexicon/config.py
semantic_lexicon/decoding_tad.py
semantic_lexicon/diagnostics.py
semantic_lexicon/embeddings.py
semantic_lexicon/generator.py
semantic_lexicon/go_no_go.py
semantic_lexicon/graph_api.py
semantic_lexicon/graph_memory.py
semantic_lexicon/intent.py
semantic_lexicon/knowledge.py
semantic_lexicon/loaders.py
semantic_lexicon/logging.py
semantic_lexicon/model.py
semantic_lexicon/oracle.py
semantic_lexicon/oracle_graph.py
semantic_lexicon/persona.py
semantic_lexicon/presentation.py
semantic_lexicon/runtime.py
semantic_lexicon/safety.py
semantic_lexicon/template_learning.py
semantic_lexicon/templates.py
semantic_lexicon/token_index.py
semantic_lexicon/training.py
semantic_lexicon/algorithms/__init__.py
semantic_lexicon/algorithms/_typing.py
semantic_lexicon/algorithms/exp3.py
semantic_lexicon/algorithms/topic_pure_retrieval.py
semantic_lexicon/analysis/__init__.py
semantic_lexicon/analysis/calibration.py
semantic_lexicon/analysis/convergence.py
semantic_lexicon/analysis/error.py
semantic_lexicon/analysis/performance.py
semantic_lexicon/analysis/regret.py
semantic_lexicon/analysis/reward.py
semantic_lexicon/analysis/validation.py
semantic_lexicon/api/__init__.py
semantic_lexicon/api/feedback.py
semantic_lexicon/data/balanced_tutor_training.jsonl
semantic_lexicon/data/cross_domain_validation.jsonl
semantic_lexicon/data/domain_hierarchy.jsonl
semantic_lexicon/data/intent.jsonl
semantic_lexicon/data/knowledge.jsonl
semantic_lexicon/pipelines/__init__.py
semantic_lexicon/utils/__init__.py
semantic_lexicon/utils/clipboard.py
semantic_lexicon/utils/install.py
semantic_lexicon/utils/io.py
semantic_lexicon/utils/random.py
semantic_lexicon/utils/text.py
semantic_lexicon-0.1.4.dist-info/licenses/LICENSE
tadkit/__init__.py
tadkit/cli.py
tadkit/core.py
semantic_lexicon-0.1.4.dist-info/METADATA
semantic_lexicon-0.1.4.dist-info/WHEEL
semantic_lexicon-0.1.4.dist-info/entry_points.txt
semantic_lexicon-0.1.4.dist-info/top_level.txt
semantic_lexicon-0.1.4.dist-info/RECORD
