Metadata-Version: 2.4
Name: semantic-lexicon
Version: 0.1.4
Summary: Neural semantic modeling toolkit with persona-aware generation and diagnostics.
Author: Semantic Lexicon Team
License:                                  Apache License
Project-URL: Homepage, https://github.com/farukalpay/Semantic-Lexicon
Project-URL: Documentation, https://github.com/farukalpay/Semantic-Lexicon#readme
Project-URL: Issues, https://github.com/farukalpay/Semantic-Lexicon/issues
Keywords: nlp,semantics,persona,knowledge-graph,cli
Classifier: Development Status :: 3 - Alpha
Classifier: Intended Audience :: Science/Research
Classifier: License :: OSI Approved :: MIT License
Classifier: Programming Language :: Python
Classifier: Programming Language :: Python :: 3
Classifier: Programming Language :: Python :: 3.9
Classifier: Programming Language :: Python :: 3.10
Classifier: Programming Language :: Python :: 3.11
Classifier: Programming Language :: Python :: 3.12
Requires-Python: >=3.9
License-File: LICENSE
Requires-Dist: numpy<2.0,>=1.23
Requires-Dist: typer<0.20,>=0.13
Requires-Dist: PyYAML<7.0,>=6.0
Requires-Dist: matplotlib<4.0,>=3.8
Provides-Extra: dev
Requires-Dist: black>=23.0; extra == "dev"
Requires-Dist: ruff>=0.4; extra == "dev"
Requires-Dist: mypy>=1.4; extra == "dev"
Requires-Dist: pytest>=7.0; extra == "dev"
Requires-Dist: pytest-cov>=4.1; extra == "dev"
Provides-Extra: docs
Requires-Dist: mkdocs>=1.5; extra == "docs"
Requires-Dist: mkdocs-material>=9.5; extra == "docs"
Provides-Extra: tadkit
Requires-Dist: transformers>=4.37; extra == "tadkit"
Requires-Dist: torch>=2.1; extra == "tadkit"
Requires-Dist: pandas>=2.0; extra == "tadkit"
Requires-Dist: streamlit>=1.30; extra == "tadkit"
Provides-Extra: personarag
Requires-Dist: langchain>=0.2; extra == "personarag"
Requires-Dist: langchain-core>=0.2; extra == "personarag"
Requires-Dist: langchain-openai>=0.1; extra == "personarag"
Requires-Dist: langchain-community>=0.2; extra == "personarag"
Requires-Dist: langgraph>=0.0.64; extra == "personarag"
Requires-Dist: faiss-cpu>=1.7; extra == "personarag"
Requires-Dist: openai>=1.0; extra == "personarag"
Dynamic: license-file
